experimentor/__init__.py
Experimentor-0.0.1.dist-info/METADATA
Experimentor-0.0.1.dist-info/WHEEL
Experimentor-0.0.1.dist-info/top_level.txt
Experimentor-0.0.1.dist-info/RECORD
